{
  "name": "OrderFlow — WhatsApp Bot",
  "nodes": [
    {
      "id": "node-webhook",
      "name": "WhatsApp Webhook",
      "type": "n8n-nodes-base.webhook",
      "typeVersion": 2,
      "position": [200, 300],
      "parameters": {
        "path": "whatsapp",
        "responseMode": "responseNode",
        "options": { "rawBody": true }
      }
    },
    {
      "id": "node-route-method",
      "name": "GET ou POST?",
      "type": "n8n-nodes-base.if",
      "typeVersion": 2,
      "position": [460, 300],
      "parameters": {
        "conditions": {
          "options": { "caseSensitive": true },
          "conditions": [
            {
              "leftValue": "={{ $json.headers['x-forwarded-for'] !== undefined ? $request.method : $json.method }}",
              "rightValue": "GET",
              "operator": { "type": "string", "operation": "notEquals" }
            }
          ]
        }
      }
    },
    {
      "id": "node-meta-verify",
      "name": "Vérification Meta",
      "type": "n8n-nodes-base.code",
      "typeVersion": 2,
      "position": [720, 480],
      "parameters": {
        "jsCode": "const query = $input.first().json.query || {};\nconst mode      = query['hub.mode'];\nconst token     = query['hub.verify_token'];\nconst challenge = query['hub.challenge'];\nconst VERIFY_TOKEN = $env.ORDERFLOW_VERIFY_TOKEN || 'mon-verify-token-secret';\nif (mode === 'subscribe' && token === VERIFY_TOKEN) {\n  return [{ json: { challenge, status: 200 } }];\n}\nreturn [{ json: { error: 'Forbidden', status: 403 } }];"
      }
    },
    {
      "id": "node-respond-verify",
      "name": "Répondre à Meta",
      "type": "n8n-nodes-base.respondToWebhook",
      "typeVersion": 1,
      "position": [980, 480],
      "parameters": {
        "respondWith": "text",
        "responseBody": "={{ $json.challenge }}",
        "options": { "responseCode": "={{ $json.status }}" }
      }
    },
    {
      "id": "node-ack-meta",
      "name": "ACK 200 à Meta",
      "type": "n8n-nodes-base.respondToWebhook",
      "typeVersion": 1,
      "position": [720, 300],
      "parameters": {
        "respondWith": "json",
        "responseBody": "{}",
        "options": { "responseCode": 200 }
      }
    },
    {
      "id": "node-extract-message",
      "name": "Extraire le message",
      "type": "n8n-nodes-base.code",
      "typeVersion": 2,
      "position": [980, 300],
      "parameters": {
        "jsCode": "const body = $input.first().json.body || $input.first().json;\nconst entry   = body?.entry?.[0];\nconst changes = entry?.changes?.[0]?.value;\nif (!changes?.messages?.length) return [];\nconst message       = changes.messages[0];\nconst phoneNumberId = changes.metadata?.phone_number_id;\nconst senderPhone   = message.from;\nconst messageType   = message.type;\nlet messageText = '';\nif (messageType === 'text') {\n  messageText = message.text?.body?.trim() || '';\n} else if (messageType === 'interactive') {\n  messageText = message.interactive?.button_reply?.id || message.interactive?.list_reply?.id || '';\n}\nreturn [{ json: { phoneNumberId, senderPhone, messageText, messageType, rawMessage: message } }];"
      }
    },
    {
      "id": "node-get-tenant",
      "name": "Charger config tenant",
      "type": "n8n-nodes-base.httpRequest",
      "typeVersion": 4.2,
      "position": [1240, 300],
      "parameters": {
        "method": "GET",
        "url": "={{ $env.SUPABASE_URL }}/rest/v1/tenants?phone_number_id=eq.{{ $json.phoneNumberId }}&is_active=eq.true&select=*",
        "authentication": "genericCredentialType",
        "genericAuthType": "httpHeaderAuth",
        "sendHeaders": true,
        "headerParameters": {
          "parameters": [
            { "name": "apikey",        "value": "={{ $env.SUPABASE_SERVICE_KEY }}" },
            { "name": "Authorization", "value": "=Bearer {{ $env.SUPABASE_SERVICE_KEY }}" }
          ]
        }
      }
    },
    {
      "id": "node-check-tenant",
      "name": "Tenant trouvé?",
      "type": "n8n-nodes-base.if",
      "typeVersion": 2,
      "position": [1500, 300],
      "parameters": {
        "conditions": {
          "conditions": [
            {
              "leftValue": "={{ $json.length }}",
              "rightValue": 0,
              "operator": { "type": "number", "operation": "gt" }
            }
          ]
        }
      }
    },
    {
      "id": "node-no-tenant",
      "name": "Ignorer (tenant inconnu)",
      "type": "n8n-nodes-base.noOp",
      "typeVersion": 1,
      "position": [1760, 480],
      "parameters": {}
    },
    {
      "id": "node-get-products",
      "name": "Charger produits",
      "type": "n8n-nodes-base.httpRequest",
      "typeVersion": 4.2,
      "position": [1760, 200],
      "parameters": {
        "method": "GET",
        "url": "={{ $env.SUPABASE_URL }}/rest/v1/products?tenant_id=eq.{{ $('Charger config tenant').item.json[0].id }}&is_available=eq.true&select=id,name,price,stock_quantity,description&order=name",
        "authentication": "genericCredentialType",
        "genericAuthType": "httpHeaderAuth",
        "sendHeaders": true,
        "headerParameters": {
          "parameters": [
            { "name": "apikey",        "value": "={{ $env.SUPABASE_SERVICE_KEY }}" },
            { "name": "Authorization", "value": "=Bearer {{ $env.SUPABASE_SERVICE_KEY }}" }
          ]
        }
      }
    },
    {
      "id": "node-get-session",
      "name": "Charger session",
      "type": "n8n-nodes-base.httpRequest",
      "typeVersion": 4.2,
      "position": [2020, 200],
      "parameters": {
        "method": "GET",
        "url": "={{ $env.SUPABASE_URL }}/rest/v1/whatsapp_sessions?tenant_id=eq.{{ $('Charger config tenant').item.json[0].id }}&phone=eq.{{ $('Extraire le message').item.json.senderPhone }}&select=*",
        "authentication": "genericCredentialType",
        "genericAuthType": "httpHeaderAuth",
        "sendHeaders": true,
        "headerParameters": {
          "parameters": [
            { "name": "apikey",        "value": "={{ $env.SUPABASE_SERVICE_KEY }}" },
            { "name": "Authorization", "value": "=Bearer {{ $env.SUPABASE_SERVICE_KEY }}" }
          ]
        }
      }
    },
    {
      "id": "node-bot-engine",
      "name": "Bot Engine",
      "type": "n8n-nodes-base.code",
      "typeVersion": 2,
      "position": [2280, 200],
      "parameters": {
        "jsCode": "const tenant   = $('Charger config tenant').item.json[0];\nconst products = $('Charger produits').all().map(i => i.json);\nconst sessions = $('Charger session').all();\nconst msg      = $('Extraire le message').item.json;\nconst sessionData = sessions.length ? sessions[0].json : null;\nconst state   = sessionData?.state   || 'INITIAL';\nconst context = sessionData?.context || {};\nconst phone = msg.senderPhone;\nconst text  = msg.messageText.trim();\n\nfunction formatCart(cart) {\n  return cart.map(item => `  • ${item.name} x${item.qty} = ${(item.price * item.qty).toLocaleString('fr-FR')} FCFA`).join('\\n');\n}\nfunction cartTotal(cart) {\n  return cart.reduce((sum, i) => sum + i.price * i.qty, 0);\n}\nfunction buildMenu(prods) {\n  return prods.map((p, i) =>\n    `${i+1}. ${p.name} — ${p.price.toLocaleString('fr-FR')} FCFA${p.stock_quantity < 5 ? ' ⚠️ stock limité' : ''}`\n  ).join('\\n');\n}\nfunction parseSelection(text, prods) {\n  const items = [];\n  const pattern = /(\\d+)\\s*[xX×]?\\s*(\\d*)/g;\n  let match;\n  while ((match = pattern.exec(text)) !== null) {\n    const idx = parseInt(match[1]) - 1;\n    const qty = match[2] ? parseInt(match[2]) : 1;\n    if (idx >= 0 && idx < prods.length && qty > 0) {\n      const prod = prods[idx];\n      items.push({ id: prod.id, name: prod.name, price: prod.price, qty });\n    }\n  }\n  return items;\n}\nfunction checkStock(cart, prods) {\n  const issues = [];\n  for (const item of cart) {\n    const prod = prods.find(p => p.id === item.id);\n    if (prod && prod.stock_quantity < item.qty) {\n      issues.push(`${item.name} (demandé: ${item.qty}, stock: ${prod.stock_quantity})`);\n    }\n  }\n  return issues;\n}\n\nlet reply = '';\nlet newState = state;\nlet newContext = { ...context };\nlet createOrder = null;\nlet stockIssues = [];\n\nconst greetings = ['bonjour', 'salut', 'hello', 'bonsoir', 'hi', 'menu', 'start', 'commencer'];\nconst isGreeting = greetings.some(g => text.toLowerCase().includes(g));\nif (isGreeting && state !== 'INITIAL') { newState = 'INITIAL'; newContext = {}; }\n\nswitch (newState) {\n  case 'INITIAL': {\n    const menu = buildMenu(products);\n    reply = `Bonjour ! 👋 Bienvenue chez *${tenant.name}*\\n\\n📋 *Notre menu :*\\n${menu}\\n\\nTapez le numéro des plats et la quantité.\\nExemple : *1 x2, 3 x1*`;\n    newState = 'BROWSE_MENU';\n    newContext = { cart: [] };\n    break;\n  }\n  case 'BROWSE_MENU': {\n    const parsed = parseSelection(text, products);\n    if (parsed.length === 0) { reply = `Je n'ai pas compris. Tapez par exemple : *1 x2, 3 x1*`; break; }\n    const cart = [...(context.cart || []), ...parsed];\n    newContext = { ...newContext, cart };\n    reply = `🛒 *Votre panier :*\\n${formatCart(cart)}\\n\\n*Total : ${cartTotal(cart).toLocaleString('fr-FR')} FCFA*\\n\\nTapez *OK* pour continuer.`;\n    newState = 'CART_REVIEW';\n    break;\n  }\n  case 'CART_REVIEW': {\n    if (text.toLowerCase() === 'ok') { reply = `Parfait 😊 Quel est votre *nom complet* ?`; newState = 'GET_NAME'; }\n    else {\n      const parsed = parseSelection(text, products);\n      if (parsed.length > 0) {\n        const cart = [...(context.cart || []), ...parsed];\n        newContext = { ...newContext, cart };\n        reply = `🛒 *Panier mis à jour :*\\n${formatCart(cart)}\\n\\n*Total : ${cartTotal(cart).toLocaleString('fr-FR')} FCFA*\\n\\nTapez *OK* pour continuer.`;\n      } else { reply = `Tapez *OK* pour valider ou envoyez des numéros pour ajouter des plats.`; }\n    }\n    break;\n  }\n  case 'GET_NAME': {\n    if (text.length < 2) { reply = `Merci de saisir votre nom complet.`; break; }\n    newContext = { ...newContext, customerName: text };\n    reply = `Merci ${text} ! 🏠 Quelle est votre *adresse de livraison* ?`;\n    newState = 'GET_ADDRESS';\n    break;\n  }\n  case 'GET_ADDRESS': {\n    if (text.length < 5) { reply = `Merci de saisir une adresse complète.`; break; }\n    newContext = { ...newContext, address: text };\n    reply = `📅 Pour quelle *date et heure* souhaitez-vous la livraison ?\\nEx : *Demain 12h* ou *15/06 à 13h30*`;\n    newState = 'GET_DATE';\n    break;\n  }\n  case 'GET_DATE': {\n    newContext = { ...newContext, deliveryDate: text };\n    const cart = context.cart || [];\n    const recap = `👤 *Nom :* ${context.customerName}\\n🏠 *Adresse :* ${context.address}\\n📅 *Livraison :* ${text}\\n\\n🛒 *Commande :*\\n${formatCart(cart)}\\n\\n💰 *Total : ${cartTotal(cart).toLocaleString('fr-FR')} FCFA*`;\n    reply = `*Récapitulatif :*\\n\\n${recap}\\n\\nTapez *OUI* pour confirmer ou *NON* pour annuler.`;\n    newState = 'CONFIRM';\n    break;\n  }\n  case 'CONFIRM': {\n    const answer = text.toLowerCase();\n    if (['oui', 'yes', 'o', 'ok', 'confirme', '✅'].includes(answer)) {\n      const cart = context.cart || [];\n      stockIssues = checkStock(cart, products);\n      if (stockIssues.length > 0) {\n        reply = `⚠️ Stock insuffisant :\\n${stockIssues.map(s => `• ${s}`).join('\\n')}\\n\\nCommande en attente de validation. Nous vous recontactons rapidement.`;\n        createOrder = { ...context, cart, status: 'stock_issue' };\n      } else {\n        reply = `✅ *Commande confirmée !*\\n\\nMerci ${context.customerName}, votre commande est enregistrée pour le ${context.deliveryDate}.\\n📞 En cas de question : ${tenant.whatsapp_number}`;\n        createOrder = { ...context, cart, status: 'confirmed' };\n      }\n      newState = 'INITIAL';\n      newContext = {};\n    } else if (['non', 'no', 'n', 'annuler', '❌'].includes(answer)) {\n      reply = `Commande annulée. À bientôt ! 👋\\n\\nTapez *Bonjour* pour recommencer.`;\n      newState = 'INITIAL';\n      newContext = {};\n    } else { reply = `Tapez *OUI* pour confirmer ou *NON* pour annuler.`; }\n    break;\n  }\n  default: {\n    reply = `Bonjour ! Tapez *Menu* pour voir nos plats. 😊`;\n    newState = 'INITIAL';\n    newContext = {};\n  }\n}\n\nreturn [{ json: { reply, newState, newContext, createOrder, stockIssues, tenantId: tenant.id, tenantName: tenant.name, whatsappToken: tenant.whatsapp_token, phoneNumberId: tenant.phone_number_id, senderPhone: phone, sessionExists: !!sessionData } }];"
      }
    },
    {
      "id": "node-send-reply",
      "name": "Envoyer réponse WhatsApp",
      "type": "n8n-nodes-base.httpRequest",
      "typeVersion": 4.2,
      "position": [2540, 200],
      "parameters": {
        "method": "POST",
        "url": "=https://graph.facebook.com/v19.0/{{ $json.phoneNumberId }}/messages",
        "authentication": "genericCredentialType",
        "genericAuthType": "httpHeaderAuth",
        "sendHeaders": true,
        "headerParameters": {
          "parameters": [
            { "name": "Authorization", "value": "=Bearer {{ $json.whatsappToken }}" },
            { "name": "Content-Type",  "value": "application/json" }
          ]
        },
        "sendBody": true,
        "contentType": "json",
        "body": "={{ JSON.stringify({ messaging_product: 'whatsapp', to: $json.senderPhone, type: 'text', text: { body: $json.reply } }) }}"
      }
    },
    {
      "id": "node-upsert-session",
      "name": "Sauvegarder session",
      "type": "n8n-nodes-base.httpRequest",
      "typeVersion": 4.2,
      "position": [2800, 200],
      "parameters": {
        "method": "POST",
        "url": "={{ $env.SUPABASE_URL }}/rest/v1/whatsapp_sessions",
        "authentication": "genericCredentialType",
        "genericAuthType": "httpHeaderAuth",
        "sendHeaders": true,
        "headerParameters": {
          "parameters": [
            { "name": "apikey",        "value": "={{ $env.SUPABASE_SERVICE_KEY }}" },
            { "name": "Authorization", "value": "=Bearer {{ $env.SUPABASE_SERVICE_KEY }}" },
            { "name": "Prefer",        "value": "resolution=merge-duplicates" }
          ]
        },
        "sendBody": true,
        "contentType": "json",
        "body": "={{ JSON.stringify({ tenant_id: $('Bot Engine').item.json.tenantId, phone: $('Bot Engine').item.json.senderPhone, state: $('Bot Engine').item.json.newState, context: $('Bot Engine').item.json.newContext }) }}"
      }
    },
    {
      "id": "node-check-order",
      "name": "Créer une commande?",
      "type": "n8n-nodes-base.if",
      "typeVersion": 2,
      "position": [3060, 200],
      "parameters": {
        "conditions": {
          "conditions": [
            {
              "leftValue": "={{ $('Bot Engine').item.json.createOrder !== null }}",
              "rightValue": true,
              "operator": { "type": "boolean", "operation": "equals" }
            }
          ]
        }
      }
    },
    {
      "id": "node-create-order",
      "name": "Créer commande en DB",
      "type": "n8n-nodes-base.httpRequest",
      "typeVersion": 4.2,
      "position": [3320, 100],
      "parameters": {
        "method": "POST",
        "url": "={{ $env.SUPABASE_URL }}/rest/v1/orders",
        "authentication": "genericCredentialType",
        "genericAuthType": "httpHeaderAuth",
        "sendHeaders": true,
        "headerParameters": {
          "parameters": [
            { "name": "apikey",        "value": "={{ $env.SUPABASE_SERVICE_KEY }}" },
            { "name": "Authorization", "value": "=Bearer {{ $env.SUPABASE_SERVICE_KEY }}" },
            { "name": "Prefer",        "value": "return=representation" }
          ]
        },
        "sendBody": true,
        "contentType": "json",
        "body": "={{ JSON.stringify({ tenant_id: $('Bot Engine').item.json.tenantId, order_number: 'ORD-WA-' + Date.now(), customer_name: $('Bot Engine').item.json.createOrder.customerName, customer_phone: $('Bot Engine').item.json.senderPhone, customer_address: $('Bot Engine').item.json.createOrder.address, delivery_date: null, channel: 'whatsapp', status: $('Bot Engine').item.json.createOrder.status, total: $('Bot Engine').item.json.createOrder.cart.reduce((s,i) => s + i.price * i.qty, 0), notes: 'Livraison demandée : ' + $('Bot Engine').item.json.createOrder.deliveryDate }) }}"
      }
    },
    {
      "id": "node-create-items",
      "name": "Créer lignes de commande",
      "type": "n8n-nodes-base.code",
      "typeVersion": 2,
      "position": [3580, 100],
      "parameters": {
        "jsCode": "const order   = $('Créer commande en DB').item.json[0] ?? $('Créer commande en DB').item.json;\nconst orderId = order.id;\nconst cart    = $('Bot Engine').item.json.createOrder.cart;\nconst items   = cart.map(item => ({ order_id: orderId, product_id: item.id || null, product_name: item.name, product_price: item.price, quantity: item.qty, subtotal: item.price * item.qty }));\nreturn [{ json: { items, orderId, livreur_id: order.livreur_id ?? null } }];"
      }
    },
    {
      "id": "node-insert-items",
      "name": "Insérer lignes en DB",
      "type": "n8n-nodes-base.httpRequest",
      "typeVersion": 4.2,
      "position": [3840, 100],
      "parameters": {
        "method": "POST",
        "url": "={{ $env.SUPABASE_URL }}/rest/v1/order_items",
        "authentication": "genericCredentialType",
        "genericAuthType": "httpHeaderAuth",
        "sendHeaders": true,
        "headerParameters": {
          "parameters": [
            { "name": "apikey",        "value": "={{ $env.SUPABASE_SERVICE_KEY }}" },
            { "name": "Authorization", "value": "=Bearer {{ $env.SUPABASE_SERVICE_KEY }}" }
          ]
        },
        "sendBody": true,
        "contentType": "json",
        "body": "={{ JSON.stringify($json.items) }}"
      }
    },
    {
      "id": "node-check-livreur-assigned",
      "name": "Livreur assigné?",
      "type": "n8n-nodes-base.if",
      "typeVersion": 2,
      "position": [4100, 100],
      "parameters": {
        "conditions": {
          "conditions": [
            {
              "leftValue": "={{ $('Créer lignes de commande').item.json.livreur_id }}",
              "rightValue": "",
              "operator": { "type": "string", "operation": "notEmpty" }
            }
          ]
        }
      }
    },
    {
      "id": "node-get-livreur",
      "name": "Charger livreur assigné",
      "type": "n8n-nodes-base.httpRequest",
      "typeVersion": 4.2,
      "position": [4360, 60],
      "parameters": {
        "method": "GET",
        "url": "={{ $env.SUPABASE_URL }}/rest/v1/livreurs?id=eq.{{ $('Créer lignes de commande').item.json.livreur_id }}&select=id,name,phone",
        "authentication": "genericCredentialType",
        "genericAuthType": "httpHeaderAuth",
        "sendHeaders": true,
        "headerParameters": {
          "parameters": [
            { "name": "apikey",        "value": "={{ $env.SUPABASE_SERVICE_KEY }}" },
            { "name": "Authorization", "value": "=Bearer {{ $env.SUPABASE_SERVICE_KEY }}" }
          ]
        }
      }
    },
    {
      "id": "node-notify-livreur",
      "name": "Notifier le livreur",
      "type": "n8n-nodes-base.httpRequest",
      "typeVersion": 4.2,
      "position": [4620, 60],
      "parameters": {
        "method": "POST",
        "url": "=https://graph.facebook.com/v19.0/{{ $('Bot Engine').item.json.phoneNumberId }}/messages",
        "authentication": "genericCredentialType",
        "genericAuthType": "httpHeaderAuth",
        "sendHeaders": true,
        "headerParameters": {
          "parameters": [
            { "name": "Authorization", "value": "=Bearer {{ $('Bot Engine').item.json.whatsappToken }}" },
            { "name": "Content-Type",  "value": "application/json" }
          ]
        },
        "sendBody": true,
        "contentType": "json",
        "body": "={{ JSON.stringify({ messaging_product: 'whatsapp', to: String($json[0].phone).replace(/[^0-9]/g, ''), type: 'text', text: { body: '🛵 *Nouvelle livraison assignée !*\\n\\n📦 Commande : ' + ($('Créer commande en DB').item.json[0] ?? $('Créer commande en DB').item.json).order_number + '\\n👤 Client : ' + $('Bot Engine').item.json.createOrder.customerName + '\\n📱 Tél. : ' + $('Bot Engine').item.json.senderPhone + '\\n📍 Adresse : ' + $('Bot Engine').item.json.createOrder.address + '\\n📅 Livraison : ' + $('Bot Engine').item.json.createOrder.deliveryDate + '\\n💰 Total : ' + Number(($('Créer commande en DB').item.json[0] ?? $('Créer commande en DB').item.json).total).toLocaleString('fr-FR') + ' FCFA\\n\\nRépondez *OK* pour confirmer la prise en charge.' } }) }}"
      }
    }
  ],
  "connections": {
    "WhatsApp Webhook":         { "main": [[{ "node": "GET ou POST?",              "type": "main", "index": 0 }]] },
    "GET ou POST?":             { "main": [
                                   [{ "node": "ACK 200 à Meta",             "type": "main", "index": 0 }],
                                   [{ "node": "Vérification Meta",           "type": "main", "index": 0 }]
                                 ]},
    "Vérification Meta":        { "main": [[{ "node": "Répondre à Meta",            "type": "main", "index": 0 }]] },
    "ACK 200 à Meta":           { "main": [[{ "node": "Extraire le message",         "type": "main", "index": 0 }]] },
    "Extraire le message":      { "main": [[{ "node": "Charger config tenant",       "type": "main", "index": 0 }]] },
    "Charger config tenant":    { "main": [[{ "node": "Tenant trouvé?",              "type": "main", "index": 0 }]] },
    "Tenant trouvé?":           { "main": [
                                   [{ "node": "Charger produits",           "type": "main", "index": 0 }],
                                   [{ "node": "Ignorer (tenant inconnu)",   "type": "main", "index": 0 }]
                                 ]},
    "Charger produits":         { "main": [[{ "node": "Charger session",              "type": "main", "index": 0 }]] },
    "Charger session":          { "main": [[{ "node": "Bot Engine",                   "type": "main", "index": 0 }]] },
    "Bot Engine":               { "main": [[{ "node": "Envoyer réponse WhatsApp",     "type": "main", "index": 0 }]] },
    "Envoyer réponse WhatsApp": { "main": [[{ "node": "Sauvegarder session",          "type": "main", "index": 0 }]] },
    "Sauvegarder session":      { "main": [[{ "node": "Créer une commande?",          "type": "main", "index": 0 }]] },
    "Créer une commande?":      { "main": [
                                   [{ "node": "Créer commande en DB",       "type": "main", "index": 0 }],
                                   []
                                 ]},
    "Créer commande en DB":     { "main": [[{ "node": "Créer lignes de commande",     "type": "main", "index": 0 }]] },
    "Créer lignes de commande": { "main": [[{ "node": "Insérer lignes en DB",         "type": "main", "index": 0 }]] },
    "Insérer lignes en DB":     { "main": [[{ "node": "Livreur assigné?",             "type": "main", "index": 0 }]] },
    "Livreur assigné?":         { "main": [
                                   [{ "node": "Charger livreur assigné",    "type": "main", "index": 0 }],
                                   []
                                 ]},
    "Charger livreur assigné":  { "main": [[{ "node": "Notifier le livreur",          "type": "main", "index": 0 }]] }
  },
  "settings": {
    "executionOrder": "v1",
    "saveManualExecutions": true,
    "callerPolicy": "workflowsFromSameOwner"
  },
  "staticData": null,
  "tags": ["orderflow", "whatsapp", "traiteur"]
}
